dcalerts/__init__.py
dcalerts/contexts.py
dcalerts/decorators.py
dcalerts/messages.py
dcalerts/settings.py
dcalerts/utils.py
dcalerts-1.0.1.dist-info/LICENSE
dcalerts-1.0.1.dist-info/METADATA
dcalerts-1.0.1.dist-info/WHEEL
dcalerts-1.0.1.dist-info/top_level.txt
dcalerts-1.0.1.dist-info/RECORD
