Metadata-Version: 2.2
Name: dcalerts
Version: 1.0.1
Summary: Utilities that let you send Discord messages from code.
Author: WoolyMamooth
License: GPLv3
Project-URL: Homepage, https://github.com/WoolyMamooth/dcalerts
Keywords: discord,alert,notification,decorator,wrapper,context manager,message
Classifier: Intended Audience :: Developers
Classifier: Development Status :: 5 - Production/Stable
Classifier: License :: OSI Approved :: GNU General Public License v3 (GPLv3)
Classifier: Operating System :: OS Independent
Classifier: Programming Language :: Python :: 3.6
Classifier: Programming Language :: Python :: 3.8
Classifier: Programming Language :: Python :: 3.9
Classifier: Programming Language :: Python :: 3.10
Classifier: Programming Language :: Python :: 3.11
Requires-Python: >=3.6
License-File: LICENSE
Requires-Dist: requests==2.31.0
